CHANGES.txt
COPYRIGHT.txt
LICENSE.txt
MANIFEST.in
README.rst
setup.py
src/lovely/__init__.py
src/lovely.buildouthttp.egg-info/PKG-INFO
src/lovely.buildouthttp.egg-info/SOURCES.txt
src/lovely.buildouthttp.egg-info/dependency_links.txt
src/lovely.buildouthttp.egg-info/entry_points.txt
src/lovely.buildouthttp.egg-info/namespace_packages.txt
src/lovely.buildouthttp.egg-info/not-zip-safe
src/lovely.buildouthttp.egg-info/requires.txt
src/lovely.buildouthttp.egg-info/top_level.txt
src/lovely/buildouthttp/__init__.py
src/lovely/buildouthttp/buildouthttp.py
src/lovely/buildouthttp/install.txt
src/lovely/buildouthttp/tests.py