Metadata-Version: 1.1
Name: lovely.buildouthttp
Version: 0.5.0
Summary: Buildout extension to add http authentication for find-links and download recipies
Home-page: http://github.com/lovelysystems/lovely.buildouthttp
Author: Lovely Systems GmbH
Author-email: office@lovelysystems.com
License: ZPL 2.1
Keywords: buildout http authentication github
Platform: UNKNOWN
Classifier: Development Status :: 5 - Production/Stable
Classifier: Intended Audience :: Developers
Classifier: License :: OSI Approved :: Zope Public License
Classifier: Topic :: Software Development :: Build Tools
Classifier: Topic :: Software Development :: Libraries :: Python Modules
